pfmt/__init__.py
pfmt/_modidx.py
pfmt/byte.py
pfmt/numb.py
pfmt/path.py
pfmt/unit.py
pfmt/word.py
pfmt-0.0.4.dist-info/LICENSE
pfmt-0.0.4.dist-info/METADATA
pfmt-0.0.4.dist-info/WHEEL
pfmt-0.0.4.dist-info/entry_points.txt
pfmt-0.0.4.dist-info/top_level.txt
pfmt-0.0.4.dist-info/RECORD
